{
  "name": "Toms Rozits",
  "country": "Latvia",
  "age": 32,
  "date_of_birth": "1999-03-07",
  "professional_expirience_years": 5,
  "height_cm": 184.0,
  "weight_kg": 85.0,
  "bicep_cm": 45.0,
  "forearm_cm": 39.0,
  "hand_size_cm": null,
  "wingspan_cm": null,
  "grip_strength_kg": null,
  "dominant_arm": "Left",
  "pulling_style": [
    "Hook",
    "Toproll",
    "Press"
  ],
  "titles": [
    "East vs West 11 Champion (95kg Left)",
    "East vs West 12 Champion (95kg Left)",
    "East vs West 13 Champion (95kg Left)",
    "East vs West 14 Champion (95kg Left)",
    "East vs West 16 Champion (95kg Left)"
  ],
  "recent_opponents": [
    "Davit Arabuli",
    "Krasimir Kostadinov",
    "Mindaugas Tarasaitis"
  ],
  "notable_victories": [
    "Krasimir Kostadinov (x3)",
    "Davit Arabuli (x2)",
    "Mindaugas Tarasaitis"
  ],
  "injuries": [],
  "training_location": "Riga, Latvia",
  "coach": null,
  "preferred_start_position": "Center Setup",
  "strength_metrics": {
    "bench_press_kg": null,
    "curl_kg": null,
    "wrist_curl_kg": null,
    "backpressure_kg": null,
    "sidepressure_kg": null
  },
  "career_highlights": [
    "Undefeated streak in East vs West (95kg Left) through 2023-2024",
    "5 consecutive East vs West victories in 95kg left-hand division",
    "Featured on 'Armwrestling TV' as rising European star"
  ],
  "win_loss_record": {
    "right": {
      "wins": 1,
      "losses": 0
    },
    "left": {
      "wins": 0,
      "losses": 0
    }
  },
  "matches": {
    "Justin Bishop": {
      "arm": "Right",
      "date": "July 29, 2023",
      "result": "Win",
      "score": "3-0"
    }
  },
  "nickname": null,
  "occupation": null,
  "wrist_cm": null
}